{
  "id": "34ad6f3e-892e-48a5-9ace-aa86bd070a46",
  "prevId": "3ad1b80e-d69b-47c9-972f-0739da8708d7",
  "version": "7",
  "dialect": "postgresql",
  "tables": {
    "public.concept_explanations": {
      "name": "concept_explanations",
      "schema": "",
      "columns": {
        "id": {
          "name": "id",
          "type": "uuid",
          "primaryKey": true,
          "notNull": true,
          "default": "gen_random_uuid()"
        },
        "node_id": {
          "name": "node_id",
          "type": "uuid",
          "primaryKey": false,
          "notNull": true
        },
        "concept": {
          "name": "concept",
          "type": "text",
          "primaryKey": false,
          "notNull": true
        },
        "concept_original": {
          "name": "concept_original",
          "type": "text",
          "primaryKey": false,
          "notNull": true
        },
        "explanation": {
          "name": "explanation",
          "type": "text",
          "primaryKey": false,
          "notNull": true
        },
        "model_id": {
          "name": "model_id",
          "type": "text",
          "primaryKey": false,
          "notNull": false
        },
        "created_at": {
          "name": "created_at",
          "type": "timestamp with time zone",
          "primaryKey": false,
          "notNull": true,
          "default": "now()"
        }
      },
      "indexes": {},
      "foreignKeys": {
        "concept_explanations_node_id_nodes_id_fk": {
          "name": "concept_explanations_node_id_nodes_id_fk",
          "tableFrom": "concept_explanations",
          "tableTo": "nodes",
          "columnsFrom": [
            "node_id"
          ],
          "columnsTo": [
            "id"
          ],
          "onDelete": "cascade",
          "onUpdate": "no action"
        }
      },
      "compositePrimaryKeys": {},
      "uniqueConstraints": {
        "concept_explanations_node_id_concept_unique": {
          "name": "concept_explanations_node_id_concept_unique",
          "nullsNotDistinct": false,
          "columns": [
            "node_id",
            "concept"
          ]
        }
      },
      "policies": {},
      "checkConstraints": {},
      "isRLSEnabled": false
    },
    "public.node_prerequisites": {
      "name": "node_prerequisites",
      "schema": "",
      "columns": {
        "node_id": {
          "name": "node_id",
          "type": "uuid",
          "primaryKey": false,
          "notNull": true
        },
        "prerequisite_node_id": {
          "name": "prerequisite_node_id",
          "type": "uuid",
          "primaryKey": false,
          "notNull": true
        }
      },
      "indexes": {},
      "foreignKeys": {
        "node_prerequisites_node_id_nodes_id_fk": {
          "name": "node_prerequisites_node_id_nodes_id_fk",
          "tableFrom": "node_prerequisites",
          "tableTo": "nodes",
          "columnsFrom": [
            "node_id"
          ],
          "columnsTo": [
            "id"
          ],
          "onDelete": "cascade",
          "onUpdate": "no action"
        },
        "node_prerequisites_prerequisite_node_id_nodes_id_fk": {
          "name": "node_prerequisites_prerequisite_node_id_nodes_id_fk",
          "tableFrom": "node_prerequisites",
          "tableTo": "nodes",
          "columnsFrom": [
            "prerequisite_node_id"
          ],
          "columnsTo": [
            "id"
          ],
          "onDelete": "cascade",
          "onUpdate": "no action"
        }
      },
      "compositePrimaryKeys": {
        "node_prerequisites_node_id_prerequisite_node_id_pk": {
          "name": "node_prerequisites_node_id_prerequisite_node_id_pk",
          "columns": [
            "node_id",
            "prerequisite_node_id"
          ]
        }
      },
      "uniqueConstraints": {},
      "policies": {},
      "checkConstraints": {},
      "isRLSEnabled": false
    },
    "public.nodes": {
      "name": "nodes",
      "schema": "",
      "columns": {
        "id": {
          "name": "id",
          "type": "uuid",
          "primaryKey": true,
          "notNull": true,
          "default": "gen_random_uuid()"
        },
        "role_id": {
          "name": "role_id",
          "type": "uuid",
          "primaryKey": false,
          "notNull": true
        },
        "slug": {
          "name": "slug",
          "type": "text",
          "primaryKey": false,
          "notNull": true
        },
        "title": {
          "name": "title",
          "type": "text",
          "primaryKey": false,
          "notNull": true
        },
        "summary": {
          "name": "summary",
          "type": "text",
          "primaryKey": false,
          "notNull": true
        },
        "position_x": {
          "name": "position_x",
          "type": "integer",
          "primaryKey": false,
          "notNull": true,
          "default": 0
        },
        "position_y": {
          "name": "position_y",
          "type": "integer",
          "primaryKey": false,
          "notNull": true,
          "default": 0
        },
        "estimated_minutes": {
          "name": "estimated_minutes",
          "type": "integer",
          "primaryKey": false,
          "notNull": true,
          "default": 20
        },
        "mandatory": {
          "name": "mandatory",
          "type": "boolean",
          "primaryKey": false,
          "notNull": true,
          "default": true
        },
        "created_at": {
          "name": "created_at",
          "type": "timestamp with time zone",
          "primaryKey": false,
          "notNull": true,
          "default": "now()"
        }
      },
      "indexes": {},
      "foreignKeys": {
        "nodes_role_id_roles_id_fk": {
          "name": "nodes_role_id_roles_id_fk",
          "tableFrom": "nodes",
          "tableTo": "roles",
          "columnsFrom": [
            "role_id"
          ],
          "columnsTo": [
            "id"
          ],
          "onDelete": "cascade",
          "onUpdate": "no action"
        }
      },
      "compositePrimaryKeys": {},
      "uniqueConstraints": {
        "nodes_role_id_slug_unique": {
          "name": "nodes_role_id_slug_unique",
          "nullsNotDistinct": false,
          "columns": [
            "role_id",
            "slug"
          ]
        }
      },
      "policies": {},
      "checkConstraints": {},
      "isRLSEnabled": false
    },
    "public.profiles": {
      "name": "profiles",
      "schema": "",
      "columns": {
        "id": {
          "name": "id",
          "type": "uuid",
          "primaryKey": true,
          "notNull": true
        },
        "display_name": {
          "name": "display_name",
          "type": "text",
          "primaryKey": false,
          "notNull": false
        },
        "timezone": {
          "name": "timezone",
          "type": "text",
          "primaryKey": false,
          "notNull": true,
          "default": "'UTC'"
        },
        "active_role_slug": {
          "name": "active_role_slug",
          "type": "text",
          "primaryKey": false,
          "notNull": true,
          "default": "'frontend-developer'"
        },
        "explore_mode": {
          "name": "explore_mode",
          "type": "boolean",
          "primaryKey": false,
          "notNull": true,
          "default": false
        },
        "created_at": {
          "name": "created_at",
          "type": "timestamp with time zone",
          "primaryKey": false,
          "notNull": true,
          "default": "now()"
        }
      },
      "indexes": {},
      "foreignKeys": {},
      "compositePrimaryKeys": {},
      "uniqueConstraints": {},
      "policies": {},
      "checkConstraints": {},
      "isRLSEnabled": false
    },
    "public.roles": {
      "name": "roles",
      "schema": "",
      "columns": {
        "id": {
          "name": "id",
          "type": "uuid",
          "primaryKey": true,
          "notNull": true,
          "default": "gen_random_uuid()"
        },
        "slug": {
          "name": "slug",
          "type": "text",
          "primaryKey": false,
          "notNull": true
        },
        "title": {
          "name": "title",
          "type": "text",
          "primaryKey": false,
          "notNull": true
        },
        "summary": {
          "name": "summary",
          "type": "text",
          "primaryKey": false,
          "notNull": true
        },
        "status": {
          "name": "status",
          "type": "role_status",
          "typeSchema": "public",
          "primaryKey": false,
          "notNull": true,
          "default": "'draft'"
        },
        "created_at": {
          "name": "created_at",
          "type": "timestamp with time zone",
          "primaryKey": false,
          "notNull": true,
          "default": "now()"
        }
      },
      "indexes": {},
      "foreignKeys": {},
      "compositePrimaryKeys": {},
      "uniqueConstraints": {
        "roles_slug_unique": {
          "name": "roles_slug_unique",
          "nullsNotDistinct": false,
          "columns": [
            "slug"
          ]
        }
      },
      "policies": {},
      "checkConstraints": {},
      "isRLSEnabled": false
    },
    "public.skill_cards": {
      "name": "skill_cards",
      "schema": "",
      "columns": {
        "id": {
          "name": "id",
          "type": "uuid",
          "primaryKey": true,
          "notNull": true,
          "default": "gen_random_uuid()"
        },
        "node_id": {
          "name": "node_id",
          "type": "uuid",
          "primaryKey": false,
          "notNull": true
        },
        "prompt": {
          "name": "prompt",
          "type": "text",
          "primaryKey": false,
          "notNull": true
        },
        "answer_markdown": {
          "name": "answer_markdown",
          "type": "text",
          "primaryKey": false,
          "notNull": true
        },
        "kind": {
          "name": "kind",
          "type": "skill_card_kind",
          "typeSchema": "public",
          "primaryKey": false,
          "notNull": true,
          "default": "'flashcard'"
        },
        "created_at": {
          "name": "created_at",
          "type": "timestamp with time zone",
          "primaryKey": false,
          "notNull": true,
          "default": "now()"
        }
      },
      "indexes": {},
      "foreignKeys": {
        "skill_cards_node_id_nodes_id_fk": {
          "name": "skill_cards_node_id_nodes_id_fk",
          "tableFrom": "skill_cards",
          "tableTo": "nodes",
          "columnsFrom": [
            "node_id"
          ],
          "columnsTo": [
            "id"
          ],
          "onDelete": "cascade",
          "onUpdate": "no action"
        }
      },
      "compositePrimaryKeys": {},
      "uniqueConstraints": {
        "skill_cards_node_id_prompt_kind_unique": {
          "name": "skill_cards_node_id_prompt_kind_unique",
          "nullsNotDistinct": false,
          "columns": [
            "node_id",
            "prompt",
            "kind"
          ]
        }
      },
      "policies": {},
      "checkConstraints": {},
      "isRLSEnabled": false
    },
    "public.subscriptions": {
      "name": "subscriptions",
      "schema": "",
      "columns": {
        "user_id": {
          "name": "user_id",
          "type": "uuid",
          "primaryKey": true,
          "notNull": true
        },
        "stripe_customer_id": {
          "name": "stripe_customer_id",
          "type": "text",
          "primaryKey": false,
          "notNull": true
        },
        "stripe_subscription_id": {
          "name": "stripe_subscription_id",
          "type": "text",
          "primaryKey": false,
          "notNull": false
        },
        "status": {
          "name": "status",
          "type": "subscription_status",
          "typeSchema": "public",
          "primaryKey": false,
          "notNull": true
        },
        "current_period_end": {
          "name": "current_period_end",
          "type": "timestamp with time zone",
          "primaryKey": false,
          "notNull": false
        },
        "updated_at": {
          "name": "updated_at",
          "type": "timestamp with time zone",
          "primaryKey": false,
          "notNull": true,
          "default": "now()"
        }
      },
      "indexes": {},
      "foreignKeys": {},
      "compositePrimaryKeys": {},
      "uniqueConstraints": {},
      "policies": {},
      "checkConstraints": {},
      "isRLSEnabled": false
    },
    "public.tutor_messages": {
      "name": "tutor_messages",
      "schema": "",
      "columns": {
        "id": {
          "name": "id",
          "type": "uuid",
          "primaryKey": true,
          "notNull": true,
          "default": "gen_random_uuid()"
        },
        "user_id": {
          "name": "user_id",
          "type": "uuid",
          "primaryKey": false,
          "notNull": true
        },
        "node_id": {
          "name": "node_id",
          "type": "uuid",
          "primaryKey": false,
          "notNull": true
        },
        "role": {
          "name": "role",
          "type": "tutor_message_role",
          "typeSchema": "public",
          "primaryKey": false,
          "notNull": true
        },
        "content": {
          "name": "content",
          "type": "text",
          "primaryKey": false,
          "notNull": true
        },
        "model_id": {
          "name": "model_id",
          "type": "text",
          "primaryKey": false,
          "notNull": false
        },
        "created_at": {
          "name": "created_at",
          "type": "timestamp with time zone",
          "primaryKey": false,
          "notNull": true,
          "default": "now()"
        }
      },
      "indexes": {},
      "foreignKeys": {
        "tutor_messages_node_id_nodes_id_fk": {
          "name": "tutor_messages_node_id_nodes_id_fk",
          "tableFrom": "tutor_messages",
          "tableTo": "nodes",
          "columnsFrom": [
            "node_id"
          ],
          "columnsTo": [
            "id"
          ],
          "onDelete": "cascade",
          "onUpdate": "no action"
        }
      },
      "compositePrimaryKeys": {},
      "uniqueConstraints": {},
      "policies": {},
      "checkConstraints": {},
      "isRLSEnabled": false
    },
    "public.user_card_state": {
      "name": "user_card_state",
      "schema": "",
      "columns": {
        "user_id": {
          "name": "user_id",
          "type": "uuid",
          "primaryKey": false,
          "notNull": true
        },
        "card_id": {
          "name": "card_id",
          "type": "uuid",
          "primaryKey": false,
          "notNull": true
        },
        "stability": {
          "name": "stability",
          "type": "double precision",
          "primaryKey": false,
          "notNull": true,
          "default": 0
        },
        "difficulty": {
          "name": "difficulty",
          "type": "double precision",
          "primaryKey": false,
          "notNull": true,
          "default": 0
        },
        "due_at": {
          "name": "due_at",
          "type": "timestamp with time zone",
          "primaryKey": false,
          "notNull": true,
          "default": "now()"
        },
        "reps": {
          "name": "reps",
          "type": "integer",
          "primaryKey": false,
          "notNull": true,
          "default": 0
        },
        "lapses": {
          "name": "lapses",
          "type": "integer",
          "primaryKey": false,
          "notNull": true,
          "default": 0
        },
        "last_review_at": {
          "name": "last_review_at",
          "type": "timestamp with time zone",
          "primaryKey": false,
          "notNull": false
        },
        "state": {
          "name": "state",
          "type": "card_state",
          "typeSchema": "public",
          "primaryKey": false,
          "notNull": true,
          "default": "'new'"
        }
      },
      "indexes": {},
      "foreignKeys": {
        "user_card_state_card_id_skill_cards_id_fk": {
          "name": "user_card_state_card_id_skill_cards_id_fk",
          "tableFrom": "user_card_state",
          "tableTo": "skill_cards",
          "columnsFrom": [
            "card_id"
          ],
          "columnsTo": [
            "id"
          ],
          "onDelete": "cascade",
          "onUpdate": "no action"
        }
      },
      "compositePrimaryKeys": {
        "user_card_state_user_id_card_id_pk": {
          "name": "user_card_state_user_id_card_id_pk",
          "columns": [
            "user_id",
            "card_id"
          ]
        }
      },
      "uniqueConstraints": {},
      "policies": {},
      "checkConstraints": {},
      "isRLSEnabled": false
    },
    "public.user_events": {
      "name": "user_events",
      "schema": "",
      "columns": {
        "id": {
          "name": "id",
          "type": "uuid",
          "primaryKey": true,
          "notNull": true,
          "default": "gen_random_uuid()"
        },
        "user_id": {
          "name": "user_id",
          "type": "uuid",
          "primaryKey": false,
          "notNull": true
        },
        "verb": {
          "name": "verb",
          "type": "text",
          "primaryKey": false,
          "notNull": true
        },
        "object_type": {
          "name": "object_type",
          "type": "text",
          "primaryKey": false,
          "notNull": true
        },
        "object_id": {
          "name": "object_id",
          "type": "text",
          "primaryKey": false,
          "notNull": false
        },
        "payload": {
          "name": "payload",
          "type": "jsonb",
          "primaryKey": false,
          "notNull": true,
          "default": "'{}'::jsonb"
        },
        "created_at": {
          "name": "created_at",
          "type": "timestamp with time zone",
          "primaryKey": false,
          "notNull": true,
          "default": "now()"
        }
      },
      "indexes": {},
      "foreignKeys": {},
      "compositePrimaryKeys": {},
      "uniqueConstraints": {},
      "policies": {},
      "checkConstraints": {},
      "isRLSEnabled": false
    },
    "public.user_node_progress": {
      "name": "user_node_progress",
      "schema": "",
      "columns": {
        "user_id": {
          "name": "user_id",
          "type": "uuid",
          "primaryKey": false,
          "notNull": true
        },
        "node_id": {
          "name": "node_id",
          "type": "uuid",
          "primaryKey": false,
          "notNull": true
        },
        "status": {
          "name": "status",
          "type": "node_progress_status",
          "typeSchema": "public",
          "primaryKey": false,
          "notNull": true,
          "default": "'locked'"
        },
        "mastery_score": {
          "name": "mastery_score",
          "type": "double precision",
          "primaryKey": false,
          "notNull": false
        },
        "started_at": {
          "name": "started_at",
          "type": "timestamp with time zone",
          "primaryKey": false,
          "notNull": false
        },
        "mastered_at": {
          "name": "mastered_at",
          "type": "timestamp with time zone",
          "primaryKey": false,
          "notNull": false
        },
        "updated_at": {
          "name": "updated_at",
          "type": "timestamp with time zone",
          "primaryKey": false,
          "notNull": true,
          "default": "now()"
        }
      },
      "indexes": {},
      "foreignKeys": {
        "user_node_progress_node_id_nodes_id_fk": {
          "name": "user_node_progress_node_id_nodes_id_fk",
          "tableFrom": "user_node_progress",
          "tableTo": "nodes",
          "columnsFrom": [
            "node_id"
          ],
          "columnsTo": [
            "id"
          ],
          "onDelete": "cascade",
          "onUpdate": "no action"
        }
      },
      "compositePrimaryKeys": {
        "user_node_progress_user_id_node_id_pk": {
          "name": "user_node_progress_user_id_node_id_pk",
          "columns": [
            "user_id",
            "node_id"
          ]
        }
      },
      "uniqueConstraints": {},
      "policies": {},
      "checkConstraints": {},
      "isRLSEnabled": false
    }
  },
  "enums": {
    "public.card_state": {
      "name": "card_state",
      "schema": "public",
      "values": [
        "new",
        "learning",
        "review",
        "relearning"
      ]
    },
    "public.node_progress_status": {
      "name": "node_progress_status",
      "schema": "public",
      "values": [
        "locked",
        "in_progress",
        "mastered"
      ]
    },
    "public.role_status": {
      "name": "role_status",
      "schema": "public",
      "values": [
        "draft",
        "published",
        "archived"
      ]
    },
    "public.skill_card_kind": {
      "name": "skill_card_kind",
      "schema": "public",
      "values": [
        "flashcard",
        "cloze",
        "mcq"
      ]
    },
    "public.subscription_status": {
      "name": "subscription_status",
      "schema": "public",
      "values": [
        "trialing",
        "active",
        "past_due",
        "canceled",
        "unpaid",
        "incomplete",
        "incomplete_expired",
        "paused"
      ]
    },
    "public.tutor_message_role": {
      "name": "tutor_message_role",
      "schema": "public",
      "values": [
        "user",
        "assistant",
        "system"
      ]
    }
  },
  "schemas": {},
  "sequences": {},
  "roles": {},
  "policies": {},
  "views": {},
  "_meta": {
    "columns": {},
    "schemas": {},
    "tables": {}
  }
}